k2health/__init__.py
k2health/k2_health_rev2.py
k2health/pipeline.py
k2magic/__init__.py
k2magic/dataframe_db.py
k2magic/dialect/__init__.py
k2magic/dialect/calcite_dialect.py
k2magic/handler/__init__.py
k2magic/handler/k2a_handler.py
k2magic/handler/nailgun_repo_data.py
k2health-0.0.9.dist-info/METADATA
k2health-0.0.9.dist-info/WHEEL
k2health-0.0.9.dist-info/top_level.txt
k2health-0.0.9.dist-info/RECORD
