Metadata-Version: 2.1
Name: k2health
Version: 0.0.9
Summary: K2data内部的设备健康分析模板工具包
Home-page: https://www.k2data.com.cn
Author: K2data
Author-email: admin@k2data.com.cn
License: MIT License
Classifier: Development Status :: 3 - Alpha
Classifier: Intended Audience :: Developers
Classifier: License :: OSI Approved :: MIT License
Classifier: Programming Language :: Python :: 3
Classifier: Programming Language :: Python :: 3.8
Classifier: Programming Language :: Python :: 3.9
Classifier: Programming Language :: Python :: 3.10
Classifier: Operating System :: OS Independent
Classifier: Topic :: Software Development :: Libraries
Requires-Python: >=3.8
Requires-Dist: pandas
Requires-Dist: openpyxl
Requires-Dist: scikit-learn
